{
  "id": "emojis",
  "title": "Emojis",
  "items": [
    { "name": "⭐", "image": "auto" },
    { "name": "🎈", "image": "auto" },
    { "name": "🎂", "image": "auto" },
    { "name": "❤️", "image": "auto" },
    { "name": "🎁", "image": "auto" },
    { "name": "👑", "image": "auto" },
    { "name": "🌈", "image": "auto" },
    { "name": "💎", "image": "auto" },
    { "name": "🌙", "image": "auto" },
    { "name": "☀️", "image": "auto" },
    { "name": "☁️", "image": "auto" },
    { "name": "🌸", "image": "auto" },
    { "name": "🌲", "image": "auto" },
    { "name": "🐟", "image": "auto" },
    { "name": "🐦", "image": "auto" },
    { "name": "🐱", "image": "auto" },
    { "name": "🐶", "image": "auto" },
    { "name": "🚀", "image": "auto" },
    { "name": "🪐", "image": "auto" },
    { "name": "🎵", "image": "auto" },
    { "name": "🔔", "image": "auto" },
    { "name": "🔑", "image": "auto" },
    { "name": "⚓", "image": "auto" },
    { "name": "⚡", "image": "auto" },
    { "name": "🔥", "image": "auto" },
    { "name": "❄️", "image": "auto" },
    { "name": "🎲", "image": "auto" },
    { "name": "🍒", "image": "auto" },
    { "name": "🍕", "image": "auto" },
    { "name": "🍬", "image": "auto" },
    { "name": "💜", "image": "auto" },
    { "name": "🏆", "image": "auto" }
  ]
}
